Kuat/__init__.py
nopall-0.1.0.dist-info/METADATA
nopall-0.1.0.dist-info/WHEEL
nopall-0.1.0.dist-info/top_level.txt
nopall-0.1.0.dist-info/RECORD
